LICENSE
MANIFEST.in
README.md
setup.cfg
setup.py
sql30/__init__.py
sql30/api.py
sql30/cmd.py
sql30/db.py
sql30/templates/__init__.py
sql30/templates/build-table.js
sql30/templates/index.html
sql30/tests/__init_.py
sql30/tests/__init__.py
sql30/tests/sanity.py
sql30/tests/testPath.py
sql30/tests/test_context.py
sql30/tests/test_misc.py
sql30/tests/test_reviews.py
sql30/tests/test_scale_cube.py
sql30/tests/test_scale_square.py
test_sql30.egg-info/PKG-INFO
test_sql30.egg-info/SOURCES.txt
test_sql30.egg-info/dependency_links.txt
test_sql30.egg-info/top_level.txt