Metadata-Version: 2.1
Name: test-sql30
Version: 0.2.7
Summary: A zero, 0, weight ORM for sqlite3 database.
Home-page: https://github.com/gitvipin/sql30
Author: Vipin Sharma
Author-email: sh.vipin@gmail.com
License: UNKNOWN
Platform: UNKNOWN
Classifier: Programming Language :: Python :: 3
Classifier: License :: OSI Approved :: BSD License
Classifier: Operating System :: OS Independent
License-File: LICENSE
